threed4t/__init__.py
threed4t/assist.py
threed4t/audio4t.py
threed4t/common.py
threed4t/engine.py
threed4t/entity4t.py
threed4t/light4t.py
threed4t/mouse4t.py
threed4t/repl_panda.py
threed4t/sequence4t.py
threed4t/text4t.py
threed4t/model4t/cube_line.ursinamesh
threed4t/model4t/cubic6.ursinamesh
threed4t/model4t/sphere_inward.ursinamesh
threed4t/model4t/tetrahedron_line.ursinamesh
threed4t/model4t/twenty_line.ursinamesh
threed4t/texture4t/abc_grid.png
threed4t/texture4t/cubic6.svg
threed4t/texture4t/cubic6_colors.png
threed4t/texture4t/grid_white.png
threed4t/texture4t/test_grid.jpg
threed4t/texture4t/white_cube.png
threed4t/texture4t/white_gradient.png
threed4t/texture4t/圖片來源.txt
threed4t/texture4t/木箱.jpg
模擬3D模組/__init__.py
threed4t-0.0.7.dist-info/LICENSE
threed4t-0.0.7.dist-info/METADATA
threed4t-0.0.7.dist-info/WHEEL
threed4t-0.0.7.dist-info/top_level.txt
threed4t-0.0.7.dist-info/RECORD
