Metadata-Version: 2.1
Name: threed4t
Version: 0.0.7
Summary: 3d learning wraping library for Teenagers
Home-page: https://github.com/beardad1975/threed4t
Author: Wen-Hung, Chang 張文宏
Author-email: beardad1975@nmes.tyc.edu.tw
Platform: Windows
Classifier: Programming Language :: Python :: 3
Classifier: License :: OSI Approved :: MIT License
Classifier: Operating System :: Microsoft :: Windows
Classifier: Natural Language :: Chinese (Traditional)
Requires-Python: >=3.8
License-File: LICENSE
Requires-Dist: ursina (~=5.3.0)
Requires-Dist: opencv-contrib-python (>=4.7.0.68)
